tinymr/__init__.py
tinymr/_compat.py
tinymr/base.py
tinymr/bench.py
tinymr/errors.py
tinymr/memory.py
tinymr/tools.py
tinymr-0.1.dist-info/DESCRIPTION.rst
tinymr-0.1.dist-info/METADATA
tinymr-0.1.dist-info/RECORD
tinymr-0.1.dist-info/WHEEL
tinymr-0.1.dist-info/metadata.json
tinymr-0.1.dist-info/top_level.txt
tinymr-0.1.dist-info/zip-safe
