Metadata-Version: 2.0
Name: tinymr
Version: 0.1
Summary: Pythonic in-memory MapReduce.
Home-page: https://github.com/geowurster/tinymr
Author: Kevin Wurster
Author-email: wursterk@gmail.com
License: New BSD
Keywords: experimental memory map reduce mapreduce
Platform: UNKNOWN
Classifier: Topic :: Utilities
Classifier: Intended Audience :: Developers
Classifier: Development Status :: 3 - Alpha
Classifier: License :: OSI Approved :: BSD License
Classifier: Topic :: Text Processing
Classifier: Topic :: Software Development :: Libraries
Classifier: Programming Language :: Python :: 3.5
Classifier: Programming Language :: Python :: Implementation :: PyPy
Provides-Extra: all
Requires-Dist: coveralls; extra == 'all'
Requires-Dist: pytest (>=3); extra == 'all'
Requires-Dist: pytest-cov; extra == 'all'
Provides-Extra: dev
Requires-Dist: coveralls; extra == 'dev'
Requires-Dist: pytest (>=3); extra == 'dev'
Requires-Dist: pytest-cov; extra == 'dev'
